{
  "public": {},
  "private": {
    "MAIL_URL": "smtp://localhost:3000",
    "OAuth": {
      "facebook": {
        "appId": "",
        "secret": "",
        "loginStyle": "popup"
      },
      "google": {
        "clientId": "",
        "secret": "",
        "loginStyle": "popup"
      },
      "github": {
        "clientId": "",
        "secret": "",
        "loginStyle": "popup"
      },
      "instagram": {
        "clientId": "69a2169f66d84dbdb4181fb098cb34f3",
        "secret": "d0241be051e04dd9b8167a15caba1648",
        "loginStyle": "popup"
      }
    }
  }
}
